<pnp:ListInstance Title="Porteføljevisninger" Description="" DocumentTemplate="" TemplateType="100" Url="Lists/Porteføljevisninger" Hidden="true" EnableVersioning="true" MinorVersionLimit="0" MaxVersionLimit="5000" DraftVersionVisibility="0" ContentTypesEnabled="true" RemoveExistingContentTypes="true" EnableFolderCreation="false" EnableAttachments="false" 
    xmlns:pnp="http://schemas.dev.office.com/PnP/2021/03/ProvisioningSchema">
    <pnp:DataRows KeyColumn="Title" UpdateBehavior="Skip">
        <pnp:DataRow>
            <pnp:DataValue FieldName="GtSortOrder">100</pnp:DataValue>
            <pnp:DataValue FieldName="Title">Veiprosjekter</pnp:DataValue>
            <pnp:DataValue FieldName="GtSearchQuery">DepartmentId:{{sitecollectionid}} ContentTypeId:0x0100805E9E4FEAAB4F0EABAB2600D30DB70C0E*</pnp:DataValue>
            <pnp:DataValue FieldName="GtPortfolioIsDefaultView">True</pnp:DataValue>
            <pnp:DataValue FieldName="GtPortfolioFabricIcon">Car</pnp:DataValue>
            <pnp:DataValue FieldName="GtPortfolioGroupBy" />
        </pnp:DataRow>
    </pnp:DataRows>
</pnp:ListInstance>
